AUTHORS.rst
CONTRIBUTING.rst
HISTORY.rst
LICENSE
MANIFEST.in
README.rst
setup.cfg
setup.py
drf_compound_fields/__init__.py
drf_compound_fields/fields.py
drf_compound_fields.egg-info/PKG-INFO
drf_compound_fields.egg-info/SOURCES.txt
drf_compound_fields.egg-info/dependency_links.txt
drf_compound_fields.egg-info/not-zip-safe
drf_compound_fields.egg-info/requires.txt
drf_compound_fields.egg-info/top_level.txt