Metadata-Version: 1.1
Name: drf-compound-fields
Version: 2.0.0
Summary: Django-REST-framework serializer fields for compound types.
Home-page: https://github.com/estebistec/drf-compound-fields
Author: Steven Cummings
Author-email: cummingscs@gmail.com
License: BSD
Keywords: rest_framework rest apis services fields compound
Platform: UNKNOWN
Classifier: Development Status :: 4 - Beta
Classifier: Intended Audience :: Developers
Classifier: License :: OSI Approved :: BSD License
Classifier: Natural Language :: English
Classifier: Programming Language :: Python :: 3
Classifier: Programming Language :: Python :: 3.6
Classifier: Programming Language :: Python :: 3.7
Classifier: Programming Language :: Python :: Implementation :: CPython
Classifier: Programming Language :: Python :: Implementation :: PyPy
